bazeler/__init__.py
bazeler/bazeler.py
bazeler/command_line.py
bazeler/data/BUILD
bazeler/data/WORKSPACE
bazeler/data/buildfiles/Darwin/x86_64/boost_python.BUILD
bazeler/data/buildfiles/Darwin/x86_64/cuda.BUILD
bazeler/data/buildfiles/Darwin/x86_64/cudnn.BUILD
bazeler/data/buildfiles/Darwin/x86_64/cxsparse.BUILD
bazeler/data/buildfiles/Darwin/x86_64/eigen.BUILD
bazeler/data/buildfiles/Darwin/x86_64/flann.BUILD
bazeler/data/buildfiles/Darwin/x86_64/geographic.BUILD
bazeler/data/buildfiles/Darwin/x86_64/glew.BUILD
bazeler/data/buildfiles/Darwin/x86_64/glfw.BUILD
bazeler/data/buildfiles/Darwin/x86_64/glib.BUILD
bazeler/data/buildfiles/Darwin/x86_64/glm.BUILD
bazeler/data/buildfiles/Darwin/x86_64/glog.BUILD
bazeler/data/buildfiles/Darwin/x86_64/gsl.BUILD
bazeler/data/buildfiles/Darwin/x86_64/gtest.BUILD
bazeler/data/buildfiles/Darwin/x86_64/jpeg.BUILD
bazeler/data/buildfiles/Darwin/x86_64/libconfig.BUILD
bazeler/data/buildfiles/Darwin/x86_64/libgstreamer.BUILD
bazeler/data/buildfiles/Darwin/x86_64/libkml.BUILD
bazeler/data/buildfiles/Darwin/x86_64/libpcl.BUILD
bazeler/data/buildfiles/Darwin/x86_64/libpython.BUILD
bazeler/data/buildfiles/Darwin/x86_64/libxml2.BUILD
bazeler/data/buildfiles/Darwin/x86_64/lua.BUILD
bazeler/data/buildfiles/Darwin/x86_64/opencv.BUILD
bazeler/data/buildfiles/Darwin/x86_64/png.BUILD
bazeler/data/buildfiles/Darwin/x86_64/poco.BUILD
bazeler/data/buildfiles/Darwin/x86_64/protobuf.BUILD
bazeler/data/buildfiles/Darwin/x86_64/spinnaker.BUILD
bazeler/data/buildfiles/Darwin/x86_64/ssl.BUILD
bazeler/data/buildfiles/Darwin/x86_64/suitesparse.BUILD
bazeler/data/buildfiles/Darwin/x86_64/tbb.BUILD
bazeler/data/buildfiles/Darwin/x86_64/tiff.BUILD
bazeler/data/buildfiles/Darwin/x86_64/v4l.BUILD
bazeler/data/buildfiles/Linux/aarch64/cereal.BUILD
bazeler/data/buildfiles/Linux/aarch64/cuda.BUILD
bazeler/data/buildfiles/Linux/aarch64/cudnn.BUILD
bazeler/data/buildfiles/Linux/aarch64/cxsparse.BUILD
bazeler/data/buildfiles/Linux/aarch64/eigen.BUILD
bazeler-0.0.12.dist-info/LICENSE.txt
bazeler-0.0.12.dist-info/METADATA
bazeler-0.0.12.dist-info/WHEEL
bazeler-0.0.12.dist-info/entry_points.txt
bazeler-0.0.12.dist-info/top_level.txt
bazeler-0.0.12.dist-info/RECORD
