Metadata-Version: 2.1
Name: bazeler
Version: 0.0.12
Summary: Bazel helper package
Home-page: https://github.com/iabaldwin/bazeler
Author: Ian Baldwin
Author-email: ian@iabaldwin.com
License: UNKNOWN
Platform: UNKNOWN
Classifier: Programming Language :: Python :: 3
Classifier: Operating System :: OS Independent
Requires-Python: >=3.6
Requires-Dist: jinja2
Requires-Dist: colorama
